otwrapy/__init__.py
otwrapy/_otwrapy.py
otwrapy/examples/__init__.py
otwrapy/examples/beam/CMakeLists.txt
otwrapy/examples/beam/__init__.py
otwrapy/examples/beam/_probability_model.py
otwrapy/examples/beam/beam
otwrapy/examples/beam/beam.c
otwrapy/examples/beam/beam.exe
otwrapy/examples/beam/beam_input_template.xml
otwrapy/examples/beam/beam_wrapper
otwrapy/examples/beam/sample_E.csv
otwrapy/examples/beam/wrapper.py
otwrapy/examples/beam/__pycache__/__init__.cpython-314.pyc
otwrapy/examples/beam/__pycache__/_probability_model.cpython-314.pyc
otwrapy/examples/beam/__pycache__/wrapper.cpython-314.pyc
otwrapy-0.13.dist-info/licenses/COPYING
otwrapy-0.13.dist-info/licenses/COPYING.LESSER
otwrapy-0.13.dist-info/METADATA
otwrapy-0.13.dist-info/WHEEL
otwrapy-0.13.dist-info/top_level.txt
otwrapy-0.13.dist-info/RECORD
