Metadata-Version: 2.4
Name: otwrapy
Version: 0.13
Summary: Simplify wrapping of external codes
Author: Felipe Aguirre Martinez, Julien Schueller
License: LGPL-3.0-or-later
Project-URL: Homepage, https://github.com/openturns/otwrapy
Project-URL: Documentation, http://openturns.github.io/otwrapy/master/
Project-URL: Repository, https://github.com/openturns/otwrapy.git
Keywords: wrapping
Classifier: Intended Audience :: Science/Research
Classifier: Natural Language :: English
Classifier: Topic :: Scientific/Engineering
License-File: COPYING
License-File: COPYING.LESSER
Requires-Dist: openturns
Requires-Dist: tqdm
Provides-Extra: doc
Requires-Dist: numpydoc; extra == "doc"
Requires-Dist: sphinx; extra == "doc"
Provides-Extra: all
Requires-Dist: joblib; extra == "all"
Requires-Dist: ipyparallel; extra == "all"
Requires-Dist: pathos; extra == "all"
Requires-Dist: dask; extra == "all"
Dynamic: license-file
